{
  "appPageId" : "4c4cb39a-4361-4b52-9eb7-bc194ca2db38",
  "componentName" : "siteforce:sldsOneColLayout",
  "id" : "b1f0cbb0-fcaa-481f-af25-492d38fd4207",
  "label" : "Record List",
  "regions" : [ {
    "id" : "f8393f4a-2303-488a-bc7d-1ea1f767ac1a",
    "regionName" : "header",
    "type" : "region"
  }, {
    "components" : [ {
      "componentAttributes" : {
        "enableInlineEdit" : false,
        "filterName" : "{!filterId}",
        "layout" : "STANDARD",
        "pageSize" : 25,
        "scope" : "{!objectName}",
        "showActionBar" : false,
        "showChartsPanel" : false,
        "showDisplay" : "grid",
        "showFilterPanel" : false,
        "showImageIcon" : false,
        "showManualRefreshButton" : false,
        "showObjectName" : false,
        "showPinnedList" : false,
        "showSearchBar" : false
      },
      "componentName" : "forceCommunity:objectHome",
      "id" : "31bb04a5-9019-4bba-8c55-699e80dfc99b",
      "renderPriority" : "NEUTRAL",
      "renditionMap" : { },
      "type" : "component"
    } ],
    "id" : "978f9dee-d8a6-4cff-9637-6e10472bf97a",
    "regionName" : "content",
    "type" : "region"
  }, {
    "id" : "b0c4406b-4929-4bab-90f0-d6251b45983c",
    "regionName" : "footer",
    "type" : "region"
  } ],
  "themeLayoutType" : "Inner",
  "type" : "view",
  "viewType" : "list"
}